{
  "$schema": "https://turbo.build/schema.json",
  "ui": "stream",
  "tasks": {
    "build": {
      "dependsOn": ["^build"],
      "outputs": ["dist/**", ".astro/**", "build/**"]
    },
    "dev": {
      "cache": false,
      "persistent": true
    },
    "lint": {
      "outputs": []
    },
    "typecheck": {
      "dependsOn": ["^build"],
      "outputs": []
    },
    "test": {
      "dependsOn": ["^build"],
      "outputs": ["coverage/**"]
    },
    "tokens:build": {
      "outputs": ["dist/**"]
    }
  }
}
